[
  {
    "type": "paragraph",
    "children": [
      {
        "text": "Irure aliquip reprehenderit sint ullamco voluptate tempor voluptate minim labore. Duis cupidatat dolore sunt. Occaecat duis consequat ex id minim tempor id exercitation amet. Elit ullamco in duis labore non sint mollit culpa dolore elit consequat. Est sit cillum excepteur anim ut eu do dolor. Anim mollit veniam minim sint cupidatat adipisicing ea ut sit. Sit eu irure deserunt elit labore dolore."
      }
    ]
  },
  {
    "type": "paragraph",
    "children": [
      {
        "text": "\n"
      }
    ]
  },
  {
    "type": "paragraph",
    "children": [
      {
        "text": "Reprehenderit fugiat exercitation ut. Sint non consectetur proident. Pariatur laboris anim esse labor"
      }
    ]
  }
]